Metadata-Version: 2.4
Name: artcafe-agent-framework
Version: 0.4.3
Summary: A flexible, modular framework for building intelligent, collaborative AI agents
Home-page: https://github.com/artcafeai/agent-framework
Author: ArtCafe Team
Author-email: "ArtCafe.ai" <support@artcafe.ai>
Maintainer-email: "ArtCafe.ai" <support@artcafe.ai>
License: MIT License
Project-URL: Homepage, https://artcafe.ai
Project-URL: Documentation, https://docs.artcafe.ai/agent-framework
Project-URL: Repository, https://github.com/artcafeai/artcafe-agent-framework
Project-URL: Bug Tracker, https://github.com/artcafeai/artcafe-agent-framework/issues
Project-URL: Changelog, https://github.com/artcafeai/artcafe-agent-framework/blob/main/CHANGELOG.md
Keywords: ai,agents,llm,framework,messaging,pubsub
Classifier: Development Status :: 4 - Beta
Classifier: Intended Audience :: Developers
Classifier: License :: OSI Approved :: MIT License
Classifier: Operating System :: OS Independent
Classifier: Programming Language :: Python :: 3
Classifier: Programming Language :: Python :: 3.8
Classifier: Programming Language :: Python :: 3.9
Classifier: Programming Language :: Python :: 3.10
Classifier: Programming Language :: Python :: 3.11
Classifier: Programming Language :: Python :: 3.12
Classifier: Topic :: Software Development :: Libraries :: Python Modules
Classifier: Topic :: Scientific/Engineering :: Artificial Intelligence
Requires-Python: >=3.8
License-File: LICENSE
Requires-Dist: pyyaml>=6.0
Requires-Dist: aiohttp>=3.8.0
Requires-Dist: websockets>=10.4
Requires-Dist: tiktoken>=0.3.3
Requires-Dist: cryptography>=38.0.0
Requires-Dist: nats-py>=2.5.0
Provides-Extra: dev
Requires-Dist: pytest>=7.0.0; extra == "dev"
Requires-Dist: pytest-asyncio>=0.21.0; extra == "dev"
Requires-Dist: black>=23.1.0; extra == "dev"
Requires-Dist: mypy>=1.0.0; extra == "dev"
Requires-Dist: flake8>=6.0.0; extra == "dev"
Requires-Dist: isort>=5.12.0; extra == "dev"
Provides-Extra: llm-providers
Requires-Dist: openai>=1.0.0; extra == "llm-providers"
Requires-Dist: boto3>=1.26.0; extra == "llm-providers"
Requires-Dist: anthropic>=0.20.0; extra == "llm-providers"
Provides-Extra: validation
Requires-Dist: marshmallow>=3.19.0; extra == "validation"
Requires-Dist: pydantic>=2.0.0; extra == "validation"
Provides-Extra: all
Requires-Dist: artcafe-agent-framework[dev,llm-providers,validation]; extra == "all"
Dynamic: author
Dynamic: home-page
Dynamic: license-file
Dynamic: requires-python
